README.rst
requirements.txt
setup.cfg
setup.py
./LICENSE.txt
./README.rst
src/eingefuhrt/__init__.py
src/eingefuhrt/constants.py
src/eingefuhrt/formatters.py
src/eingefuhrt/main.py
src/eingefuhrt/parser.py
src/eingefuhrt.egg-info/PKG-INFO
src/eingefuhrt.egg-info/SOURCES.txt
src/eingefuhrt.egg-info/dependency_links.txt
src/eingefuhrt.egg-info/entry_points.txt
src/eingefuhrt.egg-info/not-zip-safe
src/eingefuhrt.egg-info/pbr.json
src/eingefuhrt.egg-info/top_level.txt