Metadata-Version: 1.0
Name: eingefuhrt
Version: 0.2.0
Summary: German quality import linter and formatter for Python.
Home-page: https://github.com/acatton/eingefuhrt
Author: Antoine Catton
Author-email: devel@antoine.catton.fr
License: MIT
Keywords: import imports linter sort isort sorting hacking formatter
Platform: UNKNOWN
